setup.py
mzgtfs/__init__.py
mzgtfs/agency.py
mzgtfs/entities.py
mzgtfs/entity.py
mzgtfs/export.py
mzgtfs/fareattribute.py
mzgtfs/farerule.py
mzgtfs/feed.py
mzgtfs/frequency.py
mzgtfs/geom.py
mzgtfs/iso639.py
mzgtfs/route.py
mzgtfs/serviceperiod.py
mzgtfs/shape.py
mzgtfs/stop.py
mzgtfs/stoptime.py
mzgtfs/test_agency.py
mzgtfs/test_entity.py
mzgtfs/test_feed.py
mzgtfs/test_geom.py
mzgtfs/test_route.py
mzgtfs/test_stop.py
mzgtfs/test_stoptime.py
mzgtfs/test_trip.py
mzgtfs/test_util.py
mzgtfs/transfer.py
mzgtfs/trip.py
mzgtfs/util.py
mzgtfs/validate.py
mzgtfs/validation.py
mzgtfs/widetime.py
mzgtfs.egg-info/PKG-INFO
mzgtfs.egg-info/SOURCES.txt
mzgtfs.egg-info/dependency_links.txt
mzgtfs.egg-info/not-zip-safe
mzgtfs.egg-info/requires.txt
mzgtfs.egg-info/top_level.txt
mzgtfs/examples/sample-feed-multipleagencies.zip
mzgtfs/examples/sample-feed.zip