Metadata-Version: 1.0
Name: mzgtfs
Version: 0.10.2
Summary: Mapzen GTFS
Home-page: https://github.com/transitland/mapzen-gtfs
Author: Ian Rees
Author-email: ian@mapzen.com
License: License :: OSI Approved :: MIT License
Platform: UNKNOWN
